{
  "6": [
    "/images/post6_a_poster.jpg",
    "/images/post6_b_poster.jpg"
  ],
  "8": [
    "/images/post8_poster.jpg"
  ],
  "10": [
    "/images/post10_a_poster.jpg",
    "/images/post10_b_poster.jpg"
  ],
  "21": [
    "/images/post21_a_poster.jpg",
    "/images/post21_b_poster.jpg"
  ],
  "22": [
    "/images/post22_a_poster.jpg",
    "/images/post22_b_poster.jpg"
  ],
  "23": [
    "/images/post23_a_poster.jpg",
    "/images/post23_b_poster.jpg"
  ],
  "25": [
    "/images/post25_a_poster.jpg",
    "/images/post25_b_poster.jpg"
  ],
  "28": [
    "/images/post28_a_poster.jpg",
    "/images/post28_b_poster.jpg"
  ],
  "29": [
    "/images/post29_a_poster.jpg",
    "/images/post29_b_poster.jpg"
  ],
  "30": [
    "/images/post30_a_poster.jpg",
    "/images/post30_b_poster.jpg"
  ],
  "36": [
    "/images/post36_a_poster.jpg",
    "/images/post36_b_poster.jpg"
  ]
}